pyworld/__init__.py
pyworld/pyworld.cp310-win_amd64.pyd
pyworld-0.3.5.dist-info/LICENSE
pyworld-0.3.5.dist-info/METADATA
pyworld-0.3.5.dist-info/WHEEL
pyworld-0.3.5.dist-info/top_level.txt
pyworld-0.3.5.dist-info/RECORD
