Metadata-Version: 2.1
Name: pyworld
Version: 0.3.5
Summary: PyWorld: a Python wrapper for WORLD vocoder
Home-page: https://github.com/JeremyCCHsu/Python-Wrapper-for-World-Vocoder
Author: Pyworld Contributors
Author-email: jeremycchsu@gmail.com
License: UNKNOWN
Keywords: vocoder
Platform: UNKNOWN
License-File: LICENSE
Requires-Dist: numpy
Provides-Extra: sdist
Requires-Dist: numpy ; extra == 'sdist'
Requires-Dist: cython (>=0.24) ; extra == 'sdist'
Provides-Extra: test
Requires-Dist: nose ; extra == 'test'
